tritium_remote_py/__init__.py
tritium_remote_py/client.py
tritium_remote_py/connect.py
tritium_remote_py/exceptions.py
tritium_remote_py/connection/__init__.py
tritium_remote_py/connection/mock.py
tritium_remote_py/connection/websocket.py
tritium_remote_py/graphql/__init__.py
tritium_remote_py/graphql/live_query.py
tritium_remote_py/graphql/operation.py
tritium_remote_py/graphql/query.py
tritium_remote_py/graphql/subscription.py
tritium_remote_py/mixins/__init__.py
tritium_remote_py/mixins/basic_system_info.py
tritium_remote_py/mixins/messages.py
tritium_remote_py/mixins/scripts.py
tritium_remote_py/mixins/sequences.py
tritium_remote_py-1.1.3.dist-info/METADATA
tritium_remote_py-1.1.3.dist-info/WHEEL
tritium_remote_py-1.1.3.dist-info/top_level.txt
tritium_remote_py-1.1.3.dist-info/RECORD
