Metadata-Version: 2.4
Name: tritium-remote-py
Version: 1.1.3
Summary: Tritium remote interaction.
Home-page: http://wiki.engineeredarts.co.uk/tritium
Author: Engineered Arts Ltd
Author-email: tritium@engineeredarts.co.uk
License: GPL
Keywords: tritium robotics
Classifier: Development Status :: 5 - Production/Stable
Classifier: License :: OSI Approved :: GNU General Public License (GPL)
Classifier: Environment :: No Input/Output (Daemon)
Classifier: Operating System :: POSIX :: Linux
Classifier: Programming Language :: Python :: 3.8
Classifier: Programming Language :: Python :: 3 :: Only
Classifier: Topic :: Scientific/Engineering
Classifier: Framework :: Robot Framework :: Library
Requires-Dist: websockets<16,>=15
Dynamic: author
Dynamic: author-email
Dynamic: classifier
Dynamic: description
Dynamic: home-page
Dynamic: keywords
Dynamic: license
Dynamic: requires-dist
Dynamic: summary
